natspy_lock/__init__.py
natspy_lock/lock.py
natspy_lock-0.2.0.dist-info/METADATA
natspy_lock-0.2.0.dist-info/WHEEL
natspy_lock-0.2.0.dist-info/licenses/LICENSE.txt
natspy_lock-0.2.0.dist-info/RECORD
