Metadata-Version: 2.1
Name: natspy-lock
Version: 0.2.0
Summary: Distributed lock library using nats.py
Project-URL: Documentation, https://github.com/HHongSeungWoo/natspy-lock#readme
Project-URL: Issues, https://github.com/HHongSeungWoo/natspy-lock/issues
Project-URL: Source, https://github.com/HHongSeungWoo/natspy-lock
Author-email: Seungwoo Hong <qksn1541@gmail.com>
License-Expression: MIT
License-File: LICENSE.txt
Keywords: Distributed lock,nats.py,python lock
Classifier: Development Status :: 4 - Beta
Classifier: Programming Language :: Python
Classifier: Programming Language :: Python :: 3.7
Classifier: Programming Language :: Python :: 3.8
Classifier: Programming Language :: Python :: 3.9
Classifier: Programming Language :: Python :: 3.10
Classifier: Programming Language :: Python :: 3.11
Classifier: Programming Language :: Python :: 3.12
Classifier: Programming Language :: Python :: Implementation :: CPython
Classifier: Programming Language :: Python :: Implementation :: PyPy
Requires-Python: >=3.7
Requires-Dist: nats-py>=2.0.0
